algol_bayer-2025.12.1.data/scripts/bayer_capture_histograms.sh
algol_bayer-2025.12.1.data/scripts/bayer_capture_images.sh
algol_bayer-2025.12.1.data/scripts/bayer_capture_spectra.sh
algol_bayer-2025.12.1.data/scripts/reset-camera.sh
algol_bayer-2025.12.1.dist-info/licenses/LICENSE
bayer/__init__.py
bayer/extraction.py
bayer/to_rgb.py
bayer/utils.py
bayer/scripts/__init__.py
bayer/scripts/darkflat.py
bayer/scripts/debayer.py
bayer/scripts/display_histogram.py
bayer/scripts/display_image.py
bayer/scripts/display_spectrum.py
bayer/scripts/visualize_segmentation.py
algol_bayer-2025.12.1.dist-info/METADATA
algol_bayer-2025.12.1.dist-info/WHEEL
algol_bayer-2025.12.1.dist-info/entry_points.txt
algol_bayer-2025.12.1.dist-info/top_level.txt
algol_bayer-2025.12.1.dist-info/RECORD
